pyintan/__init__.py
pyintan/core.py
pyintan/intan.py
pyintan/tools.py
pyintan/version.py
pyintan-0.2.1.dist-info/LICENSE
pyintan-0.2.1.dist-info/METADATA
pyintan-0.2.1.dist-info/WHEEL
pyintan-0.2.1.dist-info/top_level.txt
pyintan-0.2.1.dist-info/RECORD
