Metadata-Version: 2.1
Name: pyintan
Version: 0.2.1
Summary: Python package for parsing INTAN data.
Home-page: https://github.com/alejoe91/pyintan
Author: Alessio Buccino
Author-email: alessiob@ifi.uio.no
License: UNKNOWN
Platform: UNKNOWN
Classifier: Programming Language :: Python :: 3
Classifier: License :: OSI Approved :: GNU General Public License v3 (GPLv3)
Classifier: Operating System :: OS Independent
Requires-Dist: numpy
Requires-Dist: pyyaml
Requires-Dist: quantities
